MANIFEST.in
README
setup.py
django_onec_utils.egg-info/PKG-INFO
django_onec_utils.egg-info/SOURCES.txt
django_onec_utils.egg-info/dependency_links.txt
django_onec_utils.egg-info/top_level.txt
django_onec_utils.egg-info/zip-safe
onec_utils/__init__.py
onec_utils/fields.py
onec_utils/forms.py
onec_utils/inlines.py
onec_utils/managers.py
onec_utils/middleware.py
onec_utils/models.py
onec_utils/utils.py
onec_utils/widgets.py
onec_utils/templatetags/__init__.py
onec_utils/templatetags/truncatechars.py
onec_utils/templatetags/widont.py