Metadata-Version: 1.0
Name: django-onec-utils
Version: 0.2.2
Summary: A collection of misc. tools for One Cardinal's work.
Home-page: http://github.com/powellc/django-onec-utils
Author: Colin Powell
Author-email: colin@onecardinal.com
License: BSD
Download-URL: http://github.com/powellc/django-onec-utils/downloads
Platform: UNKNOWN
Classifier: Development Status :: 4 - Beta
Classifier: Environment :: Web Environment
Classifier: Intended Audience :: Developers
Classifier: License :: OSI Approved :: BSD License
Classifier: Operating System :: OS Independent
Classifier: Programming Language :: Python
Classifier: Framework :: Django
